PhysicsNum/Exponential.py
PhysicsNum/Gaussianfit.py
PhysicsNum/ImportData.py
PhysicsNum/Linearreg.py
PhysicsNum/Riemann.py
PhysicsNum/__init__.py
PhysicsNum-0.1.1.dist-info/LICENSE
PhysicsNum-0.1.1.dist-info/METADATA
PhysicsNum-0.1.1.dist-info/WHEEL
PhysicsNum-0.1.1.dist-info/top_level.txt
PhysicsNum-0.1.1.dist-info/RECORD
