Metadata-Version: 2.1
Name: PhysicsNum
Version: 0.1.1
Summary: Numerical methods provided to solve different methods in university studies
Home-page: UNKNOWN
Author: Andreas Evensen
Author-email: Andreas.evensen11@gmail.com
License: MIT
Platform: UNKNOWN
Classifier: Development Status :: 3 - Alpha
Classifier: Intended Audience :: Developers
Classifier: License :: OSI Approved :: MIT License
